<Properties StartupConfiguration="{CC5811ED-A6AB-4A6D-A2AD-5E0E41B2BE9D}|Default">
  <MonoDevelop.Ide.Workbench />
  <MonoDevelop.Ide.Workspace ActiveConfiguration="Debug" />
  <MonoDevelop.Ide.DebuggingService.Breakpoints>
    <BreakpointStore />
  </MonoDevelop.Ide.DebuggingService.Breakpoints>
  <MonoDevelop.Ide.DebuggingService.PinnedWatches />
  <MonoDevelop.Ide.ItemProperties.LopesCorretora.SGCPS.UI PreferredExecutionTarget="MonoDevelop.Default" />
  <MultiItemStartupConfigurations />
</Properties>